num2alpha/__init__.py
num2alpha-1.0.1.dist-info/METADATA
num2alpha-1.0.1.dist-info/WHEEL
num2alpha-1.0.1.dist-info/licenses/LICENSE
num2alpha-1.0.1.dist-info/RECORD
