Metadata-Version: 2.4
Name: num2alpha
Version: 1.0.1
Summary: Converts any base-10 integer into its corresponding alphabet form, and vice versa
Project-URL: Documentation, https://github.com/groaking/num2alpha/blob/master/README.md
Project-URL: Homepage, https://github.com/groaking/num2alpha
Project-URL: Repository, https://github.com/groaking/num2alpha.git
Project-URL: Changelog, https://github.com/groaking/num2alpha/blob/master/CHANGELOG.md
Project-URL: Issues, https://github.com/groaking/num2alpha/issues
Author-email: Samarthya Lykamanuella <93555329+groaking@users.noreply.github.com>
Maintainer-email: Samarthya Lykamanuella <93555329+groaking@users.noreply.github.com>
License:                     GNU GENERAL PUBLIC LICENSE
License-File: LICENSE
Keywords: alphabet,base-10,character,conversion,integer,number,number converter,spreadsheet,string
Classifier: Development Status :: 6 - Mature
Classifier: Intended Audience :: Developers
Classifier: Intended Audience :: Education
Classifier: Intended Audience :: Other Audience
Classifier: License :: OSI Approved :: GNU General Public License v3 (GPLv3)
Classifier: Natural Language :: English
Classifier: Operating System :: OS Independent
Classifier: Programming Language :: Python :: 3
Classifier: Topic :: Software Development :: Libraries
Classifier: Topic :: Software Development :: Libraries :: Python Modules
Classifier: Topic :: Utilities
Requires-Python: >=3.2
